{
  "date": "2026-06-30",
  "fetchedAt": "2026-06-30T10:30:04.792Z",
  "contributorsMetadata": {
    "indexName": "NIFTY 50",
    "open": "24032.05",
    "high": "24035.55",
    "low": "23829.2",
    "previousClose": "23946.25",
    "last": "23865.75",
    "percChange": "-0.34",
    "change": "-80.5",
    "totalTradedVolume": "310617161",
    "totalTradedValue": "312135125861",
    "ffmc_sum": "0",
    "yearHigh": "26373.2",
    "yearLow": "22182.55",
    "pe": "20.65",
    "pb": "3.13",
    "timeVal": "30/6/2026, 4:00:04 pm"
  },
  "marketStatus": {
    "market": "Capital Market",
    "marketStatus": "Closed",
    "tradeDate": "30/6/2026, 4:00:04 pm",
    "index": "NIFTY 50",
    "last": 23865.75,
    "variation": -80.5,
    "percentChange": -0.34,
    "marketStatusMessage": null
  }
}
